calculator/__init__.py
calculator/calculator.py
calculator/extensions/__init__.py
calculator/extensions/operaciones.py
calculator/extensions/errors/__init__.py
calculator/extensions/errors/error_handler.py
calculator_terminal-1.1.3.dist-info/LICENSE
calculator_terminal-1.1.3.dist-info/METADATA
calculator_terminal-1.1.3.dist-info/WHEEL
calculator_terminal-1.1.3.dist-info/top_level.txt
calculator_terminal-1.1.3.dist-info/RECORD
