Metadata-Version: 2.1
Name: calculator-terminal
Version: 1.1.3
Summary: La mejor calculadora para tu proyecto de Python
Home-page: https://github.com/Developer-Anony/calculator
Author: Developer Anonymous#8593
Author-email: Developer Anonymous <developeranonymous_buss@hotmail.com>
License: APACHE
Project-URL: Homepage, https://github.com/Developer-Anony/calculator
Project-URL: Bug Tracker, https://github.com/Developer-Anony/calculator/issues
Classifier: Programming Language :: Python :: 3
Classifier: License :: OSI Approved :: MIT License
Classifier: Operating System :: OS Independent
Requires-Python: >=3.7
License-File: LICENSE
